LICENSE.txt
MANIFEST.in
README.rst
setup.cfg
setup.py
versioneer.py
src/PyCICADA.egg-info/PKG-INFO
src/PyCICADA.egg-info/SOURCES.txt
src/PyCICADA.egg-info/dependency_links.txt
src/PyCICADA.egg-info/entry_points.txt
src/PyCICADA.egg-info/top_level.txt
src/cicada/__init__.py
src/cicada/__main__.py
src/cicada/_version.py
src/cicada/analysis/__init__.py
src/cicada/analysis/cicada_analysis.py
src/cicada/analysis/cicada_analysis_arguments_handler.py
src/cicada/analysis/cicada_analysis_format_wrapper.py
src/cicada/analysis/cicada_analysis_nwb_wrapper.py
src/cicada/analysis/ci_analyses/__init__.py
src/cicada/analysis/ci_analyses/cicada_activity_intervals_ratio_analysis.py
src/cicada/analysis/ci_analyses/cicada_analysis_pairwise_similarity.py
src/cicada/analysis/ci_analyses/cicada_assemblies_core_analysis.py
src/cicada/analysis/ci_analyses/cicada_assemblies_gonzalez_analysis.py
src/cicada/analysis/ci_analyses/cicada_assemblies_ica_cs_analysis.py
src/cicada/analysis/ci_analyses/cicada_assemblies_ica_mp_analysis.py
src/cicada/analysis/ci_analyses/cicada_assemblies_malvache_analysis.py
src/cicada/analysis/ci_analyses/cicada_assemblies_promax_cs_analysis.py
src/cicada/analysis/ci_analyses/cicada_assemblies_promax_mp_analysis.py
src/cicada/analysis/ci_analyses/cicada_assemblies_russo_analysis.py
src/cicada/analysis/ci_analyses/cicada_assemblies_sgc_analysis.py
src/cicada/analysis/ci_analyses/cicada_assemblies_svd_analysis.py
src/cicada/analysis/ci_analyses/cicada_assemblies_tavoni_analysis.py
src/cicada/analysis/ci_analyses/cicada_behavior_quantification_analysis.py
src/cicada/analysis/ci_analyses/cicada_cell_ass_vs_intervals_analysis.py
src/cicada/analysis/ci_analyses/cicada_cells_map_analysis.py
src/cicada/analysis/ci_analyses/cicada_connectivity_graph.py
src/cicada/analysis/ci_analyses/cicada_connectivity_graphs_description.py
src/cicada/analysis/ci_analyses/cicada_deep_cinac_prediction_analysis.py
src/cicada/analysis/ci_analyses/cicada_display_raster_analysis.py
src/cicada/analysis/ci_analyses/cicada_hubs_analysis.py
src/cicada/analysis/ci_analyses/cicada_psth_analysis.py
src/cicada/analysis/ci_analyses/cicada_sce_descritpion_analysis.py
