Metadata-Version: 2.1
Name: PyCICADA
Version: 1.0.9
Summary: A Calcium Imaging Analyses Toolbox
Home-page: https://gitlab.com/cossartlab/cicada
Author: Cossart Team
Author-email: julien.denis3@gmail.com
License: UNKNOWN
Project-URL: Bug Reports, https://gitlab.com/cossartlab/cicada/issues
Project-URL: Source, https://gitlab.com/cossartlab/cicada/tree/master/src
Keywords: cicada pycicada nwb python toolbox calcium-imaging analysis gui
Platform: UNKNOWN
Classifier: Development Status :: 4 - Beta
Classifier: Intended Audience :: Science/Research
Classifier: License :: OSI Approved :: MIT License
Classifier: Programming Language :: Python :: 3.6
Classifier: Programming Language :: Python :: 3.7
Requires-Python: >=3.5, <4
